datagen/__init__.py
datagen/generators/__init__.py
datagen/generators/car.py
datagen/generators/profile.py
datagen/generators/region.py
datagen/generators/salary.py
datagen/utils/io.py
sami_datagen-0.1.1.dist-info/METADATA
sami_datagen-0.1.1.dist-info/WHEEL
sami_datagen-0.1.1.dist-info/entry_points.txt
sami_datagen-0.1.1.dist-info/top_level.txt
sami_datagen-0.1.1.dist-info/RECORD
