Metadata-Version: 2.4
Name: sami-datagen
Version: 0.1.1
Summary: A Python library for generating realistic synthetic datasets
Home-page: https://github.com/25thOliver/Datagen
Author: Sami
Author-email: Sami <os679736@gmail.com>
License: MIT
Project-URL: Homepage, https://github.com/25thOliver/Datagen
Project-URL: Documentation, https://github.com/25thOliver/Datagen#readme
Project-URL: Repository, https://github.com/25thOliver/Datagen
Project-URL: Bug Tracker, https://github.com/25thOliver/Datagenissues
Keywords: synthetic data,data generation,testing,faker,mock data
Classifier: Development Status :: 3 - Alpha
Classifier: Intended Audience :: Developers
Classifier: Topic :: Software Development :: Testing
Classifier: License :: OSI Approved :: MIT License
Classifier: Programming Language :: Python :: 3
Classifier: Programming Language :: Python :: 3.8
Classifier: Programming Language :: Python :: 3.9
Classifier: Programming Language :: Python :: 3.10
Classifier: Programming Language :: Python :: 3.11
Requires-Python: >=3.8
Requires-Dist: faker>=18.0.0
Requires-Dist: pandas>=2.0.0
Requires-Dist: numpy>=1.24.0
Provides-Extra: dev
Requires-Dist: pytest>=7.0.0; extra == "dev"
Requires-Dist: pytest-cov>=4.0.0; extra == "dev"
Requires-Dist: black>=23.0.0; extra == "dev"
Requires-Dist: flake8>=6.0.0; extra == "dev"
Requires-Dist: mypy>=1.0.0; extra == "dev"
Provides-Extra: docs
Requires-Dist: sphinx>=6.0.0; extra == "docs"
Requires-Dist: sphinx-rtd-theme>=1.2.0; extra == "docs"
Dynamic: author
Dynamic: home-page
Dynamic: requires-python
